{
  "name": "Folkert, Strategic Unraveler",
  "rarity": "rare",
  "supertype": "legendary",
  "types": [
    "planeswalker"
  ],
  "subtypes": [],
  "manaCost": {
    "colorless": 1,
    "red": 2
  },
  "rules": [
    {
      "variant": "ability",
      "content": "Whenever you discard a card, you may have ~ deal 1 damage to any target."
    },
    {
      "variant": "ability",
      "content": "+2: Discard a card. If you do, draw a card."
    },
    {
      "variant": "ability",
      "content": "+1: Discard your hand, then draw two cards."
    },
    {
      "variant": "ability",
      "content": "-4: Until end of turn, you may cast instant and sorcery spells from your graveyard. If that spell would be put into your graveyard, exile it instead."
    }
  ],
  "loyalty": 2,
  "collectorNumber": 826,
  "art": "826-folkert-strategic-unraveler-8eacb622-5dd3-4ccd-83df-f762c63ef820.png",
  "tags": {
    "status": "concept",
    "createdAt": "2025-09-02",
    "fs/rules": 0,
    "setting": "A tall red-robed light-skinned man stands inside a circular chamber filled with floating, burning scrolls. The bottom half of the picture shows the dark stone ground on which he is standing.",
    "deck": "next",
    "count": 1
  }
}
