{
  "name": "Winter Hunter",
  "rarity": "common",
  "types": [
    "creature"
  ],
  "subtypes": [
    "cat",
    "fox"
  ],
  "manaCost": {
    "colorless": 2,
    "white": 1
  },
  "rules": [
    {
      "variant": "keyword",
      "content": "lifelink"
    },
    {
      "variant": "ability",
      "content": "When ~ enters, choose one {-}"
    },
    {
      "variant": "ability",
      "content": "• Put two courage counters on another target creature you control."
    },
    {
      "variant": "ability",
      "content": "• Put a +1/+1 counter on target creature you control."
    },
    {
      "variant": "ability",
      "content": "• Gain 3 life."
    }
  ],
  "pt": {
    "power": 2,
    "toughness": 2
  },
  "collectorNumber": 204,
  "tags": {
    "status": "concept",
    "createdAt": "2025-07-24",
    "set": "kindred-paths",
    "deck": "courage",
    "count": 2
  }
}
